{
  "Projects": [
    {
      "Name": "Personal to-do list(updated2)",
      "Owner": "Jonathan",
      "Tags": [
        "Personal",
        "Shopping"
      ],
      "id": 1
    },
    {
      "Name": "Work to-do list",
      "Owner": "Jonathan",
      "Tags": [
        "Work",
        "Programming"
      ],
      "id": 2
    },
    {
      "Name": "Random remaining to-dos",
      "Owner": "Jonathan",
      "Tags": [
        "Personal",
        "Shopping",
        "Programming"
      ],
      "id": 3
    },
    {
      "Name": "TestProj",
      "Owner": "Jonathan",
      "Tags": [],
      "id": 4
    }
  ],
  "ProjectLists": [
    {
      "id": 1,
      "Name": "Shopping",
      "Owner": "Jonathan",
      "ProjectId": 1
    },
    {
      "id": 2,
      "Name": "Projects",
      "Owner": "Jonathan",
      "ProjectId": 1
    },
    {
      "id": 3,
      "Name": "Work",
      "Owner": "Jonathan",
      "ProjectId": 2
    },
    {
      "id": 4,
      "Name": "Projects",
      "Owner": "Jonathan",
      "ProjectId": 3
    },
    {
      "Name": "List1",
      "Owner": "Jonathan",
      "ProjectId": 4,
      "id": 5
    },
    {
      "Name": "List2",
      "Owner": "Jonathan",
      "Items": [],
      "ProjectId": 4,
      "id": 6
    }
  ],
  "ListItems": [
    {
      "Name": "Item1",
      "Complete": false,
      "ProjectListId": 5,
      "id": 1
    },
    {
      "Name": "Item2",
      "Complete": false,
      "ProjectListId": "4",
      "id": 2
    }
  ]
}